tmdl_parser-0.1.1.dist-info/licenses/LICENSE.txt
tmdlparser/__init__.py
tmdlparser/data_model.py
tmdlparser/parse_tmdl.py
tmdl_parser-0.1.1.dist-info/METADATA
tmdl_parser-0.1.1.dist-info/WHEEL
tmdl_parser-0.1.1.dist-info/top_level.txt
tmdl_parser-0.1.1.dist-info/RECORD
