Metadata-Version: 2.4
Name: tmdl-parser
Version: 0.1.1
Summary: A Python library to parse and process TMDL (Table Metadata Description Language) files.
Author-email: Gustavo von Atzingen <gustavo.von.atzingen@gmail.com>
License-Expression: MIT
Project-URL: Homepage, https://github.com/Atzingen/tmdl-parser
Classifier: Programming Language :: Python :: 3
Classifier: Operating System :: OS Independent
Requires-Python: >=3.10
License-File: LICENSE.txt
Dynamic: license-file
